pytemplatesforpython/__init__.py
pytemplatesforpython/abstract_prerender_zone.py
pytemplatesforpython/abstract_template.py
pytemplatesforpython/file_template.py
pytemplatesforpython/pointer_string.py
pytemplatesforpython/templates_loader.py
pytemplatesforpython-1.1.1.dist-info/LICENSE
pytemplatesforpython-1.1.1.dist-info/METADATA
pytemplatesforpython-1.1.1.dist-info/WHEEL
pytemplatesforpython-1.1.1.dist-info/top_level.txt
pytemplatesforpython-1.1.1.dist-info/RECORD
