Metadata-Version: 2.1
Name: pytemplatesforpython
Version: 1.1.1
Summary: A package for useful python templates.
Home-page: https://github.com/Chebotarev-Alexey/pytemplatesforpython
Author: Alexey-Chebotarev
License: UNKNOWN
Platform: UNKNOWN
Classifier: Programming Language :: Python :: 3
Classifier: Programming Language :: Python :: 3.8
Classifier: Programming Language :: Python :: 3.9
Classifier: Programming Language :: Python :: 3.10
Classifier: Programming Language :: Python :: 3.11
Classifier: Programming Language :: Python :: 3.12
Classifier: License :: OSI Approved :: MIT License
Classifier: Operating System :: OS Independent
Requires-Python: >=3.8
License-File: LICENSE
